CHANGES.rst
CONTRIBUTORS.rst
DEVELOP.rst
LICENSE.GPL
LICENSE.rst
MANIFEST.in
README.rst
requirements.txt
setup.cfg
setup.py
src/collective/__init__.py
src/collective.registration.egg-info/PKG-INFO
src/collective.registration.egg-info/SOURCES.txt
src/collective.registration.egg-info/dependency_links.txt
src/collective.registration.egg-info/entry_points.txt
src/collective.registration.egg-info/namespace_packages.txt
src/collective.registration.egg-info/not-zip-safe
src/collective.registration.egg-info/requires.txt
src/collective.registration.egg-info/top_level.txt
src/collective/registration/__init__.py
src/collective/registration/config.py
src/collective/registration/configure.zcml
src/collective/registration/interfaces.py
src/collective/registration/permissions.zcml
src/collective/registration/setuphandlers.py
src/collective/registration/testing.py
src/collective/registration/utils.py
src/collective/registration/vocabularies.py
src/collective/registration/browser/__init__.py
src/collective/registration/browser/configure.zcml
src/collective/registration/browser/easyform.py
src/collective/registration/browser/subscriber.py
src/collective/registration/content/__init__.py
src/collective/registration/content/configure.zcml
src/collective/registration/content/period.py
src/collective/registration/content/registration.py
src/collective/registration/content/subscriber.py
src/collective/registration/locales/collective.registration.pot
src/collective/registration/locales/update.sh
src/collective/registration/locales/fr/LC_MESSAGES/collective.registration.po
src/collective/registration/locales/nl/LC_MESSAGES/collective.registration.po
src/collective/registration/profiles/default/browserlayer.xml
src/collective/registration/profiles/default/catalog.xml
src/collective/registration/profiles/default/metadata.xml
src/collective/registration/profiles/default/rolemap.xml
src/collective/registration/profiles/default/types.xml
src/collective/registration/profiles/default/workflows.xml
src/collective/registration/profiles/default/types/EasyForm.xml
src/collective/registration/profiles/default/types/period.xml
src/collective/registration/profiles/default/types/registration.xml
src/collective/registration/profiles/default/types/subscriber.xml
src/collective/registration/profiles/uninstall/browserlayer.xml
src/collective/registration/profiles/uninstall/types.xml
